<?xml version="1.0" encoding="utf-8" standalone="yes"?>
<post>
  <author>brianbruff</author>
  <title>That pesky iOS keyboard again</title>
  <description />
  <content>&lt;p&gt;&amp;#160;&lt;/p&gt;  &lt;p&gt;In my &lt;a href="/post/2012/09/18/IPhone-remove-the-IOS-Keyboard-on-Return.aspx" target="_blank"&gt;previous post&lt;/a&gt; I showed you how to have the keyboard resign first responder status when Return is pressed.&lt;/p&gt;  &lt;p&gt;&lt;strong&gt;A little tip:&lt;/strong&gt; is that you don’t need to set the delegate in code like my previous post, you can use the connections pane and Crtl drag from the textbox delegate to the view controller in the Outlets section.&lt;/p&gt;  &lt;p&gt;&lt;a href="./image.axd?picture=Screen%20Shot%202012-10-18%20at%2012.30.27.png"&gt;&lt;img title="Screen Shot 2012-10-18 at 12.30.27" style="border-top: 0px; border-right: 0px; background-image: none; border-bottom: 0px; padding-top: 0px; padding-left: 0px; border-left: 0px; display: inline; padding-right: 0px" border="0" alt="Screen Shot 2012-10-18 at 12.30.27" src="./image.axd?picture=Screen%20Shot%202012-10-18%20at%2012.30.27_thumb.png" width="568" height="443" /&gt;&lt;/a&gt;    &lt;br /&gt;&lt;/p&gt;  &lt;h2&gt;Still not good enough&lt;/h2&gt;  &lt;p&gt;I still had a little niggle about this keyboard covering my view, I really wanted to see what I was doing, so here’s my solution.&lt;/p&gt;  &lt;p&gt;I move the view up by y amount of pixels (-120pixels in this sample).&lt;/p&gt;  &lt;p&gt;Why negative 120? Well given that your y coordinate starts at 0,0 on the top left (i think I’ve just got a flashback of OS/2 having the origin at the lower left corner… shudder…) we move upwards.&lt;/p&gt;  &lt;p&gt;Here is our beautiful UX before we start editing&lt;/p&gt;  &lt;p&gt;&lt;a href="./image.axd?picture=Screen%20Shot%202012-10-18%20at%2012.58.12.png"&gt;&lt;img title="Screen Shot 2012-10-18 at 12.58.12" style="border-top: 0px; border-right: 0px; background-image: none; border-bottom: 0px; padding-top: 0px; padding-left: 0px; border-left: 0px; display: inline; padding-right: 0px" border="0" alt="Screen Shot 2012-10-18 at 12.58.12" src="./image.axd?picture=Screen%20Shot%202012-10-18%20at%2012.58.12_thumb.png" width="132" height="244" /&gt;&lt;/a&gt;&lt;/p&gt;  &lt;p&gt;When the keyboard presents after the textbox gains first responder status it’s now covered.&lt;/p&gt;  &lt;p&gt;So we move the view up&lt;/p&gt;  &lt;p&gt;&lt;a href="./image.axd?picture=image_227.png"&gt;&lt;img title="image" style="border-top: 0px; border-right: 0px; background-image: none; border-bottom: 0px; padding-top: 0px; padding-left: 0px; border-left: 0px; display: inline; padding-right: 0px" border="0" alt="image" src="./image.axd?picture=image_thumb_227.png" width="355" height="67" /&gt;&lt;/a&gt;&lt;/p&gt;  &lt;p&gt;When we’re finished we move it back down&lt;/p&gt;  &lt;p&gt;&lt;a href="./image.axd?picture=image_228.png"&gt;&lt;img title="image" style="border-top: 0px; border-right: 0px; background-image: none; border-bottom: 0px; padding-top: 0px; padding-left: 0px; border-left: 0px; display: inline; padding-right: 0px" border="0" alt="image" src="./image.axd?picture=image_thumb_228.png" width="359" height="74" /&gt;&lt;/a&gt;&lt;/p&gt;  &lt;p&gt;&amp;#160;&lt;/p&gt;  &lt;p&gt;So how did we implement this function?&lt;/p&gt;  &lt;p&gt;&lt;a href="./image.axd?picture=image_229.png"&gt;&lt;img title="image" style="border-top: 0px; border-right: 0px; background-image: none; border-bottom: 0px; padding-top: 0px; padding-left: 0px; border-left: 0px; display: inline; padding-right: 0px" border="0" alt="image" src="./image.axd?picture=image_thumb_229.png" width="581" height="146" /&gt;&lt;/a&gt;&lt;/p&gt;  &lt;p&gt;We change the view frame to shift the y position, and we did it in an animation to give it a little jazz.. 0.6 seconds is a way too slow for my liking but it does really show off the animation for demo purposes.&lt;/p&gt;  &lt;p&gt;Here is what it ends up looking like:&lt;/p&gt;  &lt;p&gt;&lt;a href="./image.axd?picture=Screen%20Shot%202012-10-18%20at%2012.58.28.png"&gt;&lt;img title="Screen Shot 2012-10-18 at 12.58.28" style="border-top: 0px; border-right: 0px; background-image: none; border-bottom: 0px; padding-top: 0px; padding-left: 0px; border-left: 0px; display: inline; padding-right: 0px" border="0" alt="Screen Shot 2012-10-18 at 12.58.28" src="./image.axd?picture=Screen%20Shot%202012-10-18%20at%2012.58.28_thumb.png" width="132" height="244" /&gt;&lt;/a&gt;&lt;/p&gt;</content>
  <ispublished>True</ispublished>
  <isdeleted>False</isdeleted>
  <iscommentsenabled>True</iscommentsenabled>
  <pubDate>2012-10-18 05:53:55</pubDate>
  <lastModified>2015-07-09 11:04:30</lastModified>
  <raters>0</raters>
  <rating>0</rating>
  <slug>That-pesky-iOS-keyboard-again</slug>
  <tags>
    <tag>Animating the UiView over keyboard</tag>
  </tags>
  <comments />
  <categories />
  <notifications />
</post>